Driverjs/__init__.py
Driverjs/admin.py
Driverjs/api.py
Driverjs/forms.py
Driverjs/models.py
Driverjs/serializers.py
Driverjs/tests.py
Driverjs/urls.py
Driverjs/views.py
Driverjs/migrations/0001_initial.py
Driverjs/migrations/0002_driverstep_position.py
Driverjs/migrations/__init__.py
Driverjs/static/.DS_Store
Driverjs/static/__init__.py
Driverjs/static/Driverjs/css/driver.min.css
Driverjs/static/Driverjs/js/driver.min.js
Driverjs/templates/.DS_Store
Driverjs/templates/__init__.py
Driverjs/templates/Driverjs/__init__.py
Driverjs/templates/Driverjs/driver_js.html
Driverjs/templatetags/__init__.py
Driverjs/templatetags/driverjs.py
django_driverjs-0.1.4.dist-info/METADATA
django_driverjs-0.1.4.dist-info/WHEEL
django_driverjs-0.1.4.dist-info/top_level.txt
django_driverjs-0.1.4.dist-info/RECORD
